Metadata-Version: 2.1
Name: sentence-embedding-evaluation-german
Version: 0.1.8
Summary: Sentence embedding evaluation for German
Home-page: http://github.com/ulf1/sentence-embedding-evaluation-german
Author: Ulf Hamster
Author-email: 554c46@gmail.com
License: Apache License 2.0
Requires-Python: >=3.6
License-File: LICENSE
